{"timestamp":"2014-05-13T20:00:00+0530","label":"Match 38","tournamentId":{"id":2374,"name":"ipl2014","provisional":false},"tournamentLabel":"IPL 2014","scheduleEntry":{"matchId":{"name":"ipl2014-38","tournamentId":{"id":2374,"name":"ipl2014","provisional":false},"id":2461},"description":"Match 38","matchDate":"2014-05-13T20:00:00+0530","matchType":"IPLT20","matchState":"C","highlightsLink":"http://www.iplt20.com/videos/media/id/a7d41762b2644bfa997458c56d9ba560/m38-rcb-vs-dd-match-highlights","reportLink":"http://www.iplt20.com/news/2014/match-reports/5143/report-match-38-rcb-v-dd","photostreamLink":"http://www.iplt20.com/photos/225/ipl-2014-match-38-rcb-v-dd","venue":{"id":5,"fullName":"M. Chinnaswamy Stadium","shortName":"M. Chinnaswamy Stadium","city":"Bengaluru","country":"India"},"matchStatus":{"outcome":"A","text":"Royal Challengers Bangalore won by 16 runs"},"team1":{"team":{"id":9,"fullName":"Royal Challengers Bangalore","shortName":"Challengers","abbreviation":"RCB","type":"m","primaryColor":"000000","secondaryColor":"FF3245"},"innings":[{"inningsNumber":1,"runs":186,"wkts":4,"ballsFaced":120,"maxBalls":120,"allOut":false,"declared":false}]},"team2":{"team":{"id":3,"fullName":"Delhi Daredevils","shortName":"Daredevils","abbreviation":"DD","type":"m","primaryColor":"004C93","secondaryColor":"F83430"},"innings":[{"inningsNumber":2,"runs":170,"wkts":7,"ballsFaced":120,"maxBalls":120,"allOut":false,"declared":false}]},"groupName":""},"resultOnly":false,"timestampMs":1399991400000,"endTimestampMs":1400002200000,"endTimestamp":"2014-05-13T23:00:00+0530"}