{"timestamp":"2016-04-25T20:00:00+0530","label":"Match 21","tournamentId":{"id":3957,"name":"ipl2016","provisional":false},"tournamentLabel":"IPL 2016","scheduleEntry":{"matchId":{"name":"ipl2016-21","tournamentId":{"id":3957,"name":"ipl2016","provisional":false},"id":4062},"description":"Match 21","matchDate":"2016-04-25T20:00:00+0530","matchType":"IPLT20","matchState":"C","highlightsLink":"http://www.iplt20.com/videos/media/id/4862083958001/m21-kxip-vs-mi-match-highlights","reportLink":"http://www.iplt20.com/news/2016/match-reports/7422/match-report-m21-kxip-vs-mi","photostreamLink":"http://www.iplt20.com/photos/332/match-21-kxip-v-mi","venue":{"id":9,"fullName":"IS Bindra Stadium","shortName":"IS Bindra Stadium","city":"Mohali","country":"India"},"matchStatus":{"outcome":"B","text":"Mumbai Indians won by 25 runs"},"team1":{"team":{"id":4,"fullName":"Kings XI Punjab","shortName":"Kings XI","abbreviation":"KXIP","type":"m","primaryColor":"DA1F3D","secondaryColor":"FFFFFF"},"innings":[{"inningsNumber":2,"runs":164,"wkts":7,"ballsFaced":120,"maxBalls":120,"allOut":false,"declared":false}]},"team2":{"team":{"id":6,"fullName":"Mumbai Indians","shortName":"Mumbai","abbreviation":"MI","type":"m","primaryColor":"00AEEF","secondaryColor":"FFFFFF"},"innings":[{"inningsNumber":1,"runs":189,"wkts":6,"ballsFaced":120,"maxBalls":120,"allOut":false,"declared":false}]},"groupName":""},"resultOnly":false,"timestampMs":1461594600000,"endTimestampMs":1461605400000,"endTimestamp":"2016-04-25T23:00:00+0530"}