{"teams":[{"id":4787,"team":{"id":5,"fullName":"Kolkata Knight Riders","shortName":"Knight Riders","abbreviation":"KKR","type":"m","primaryColor":"6F2C91","secondaryColor":"FFFFFF"},"players":[{"id":84,"fullName":"Gautam Gambhir","shortName":"G Gambhir","nationality":"Indian","dateOfBirth":"1981-10-14","rightArmedBowl":false,"rightHandedBat":false},{"id":127,"fullName":"Robin Uthappa","shortName":"R Uthappa","nationality":"Indian","dateOfBirth":"1985-11-11","rightArmedBowl":true,"rightHandedBat":true},{"id":123,"fullName":"Manish Pandey","shortName":"M Pandey","nationality":"Indian","dateOfBirth":"1989-09-10","rightArmedBowl":false,"rightHandedBat":true},{"id":108,"fullName":"Suryakumar Yadav","shortName":"S Yadav","nationality":"Indian","dateOfBirth":"1990-09-14","rightArmedBowl":true,"rightHandedBat":true},{"id":201,"fullName":"Shakib Al Hasan","shortName":"S Al Hasan","nationality":"Bangladeshi","dateOfBirth":"1987-03-24","rightArmedBowl":false,"rightHandedBat":false},{"id":96,"fullName":"Yusuf Pathan","shortName":"Y Pathan","nationality":"Indian","dateOfBirth":"1982-11-17","rightArmedBowl":false,"rightHandedBat":true},{"id":177,"fullName":"Andre Russell","shortName":"A Russell","nationality":"West Indian","dateOfBirth":"1988-04-29","rightArmedBowl":true,"rightHandedBat":true},{"id":76,"fullName":"Piyush Chawla","shortName":"P Chawla","nationality":"Indian","dateOfBirth":"1988-12-24","rightArmedBowl":false,"rightHandedBat":false},{"id":59,"fullName":"Umesh Yadav","shortName":"U Yadav","nationality":"Indian","dateOfBirth":"1987-10-25","rightArmedBowl":true,"rightHandedBat":true},{"id":231,"fullName":"Brad Hogg","shortName":"B Hogg","nationality":"Australian","dateOfBirth":"1971-02-06","rightArmedBowl":false,"rightHandedBat":false},{"id":169,"fullName":"Morne Morkel","shortName":"M Morkel","nationality":"South African","dateOfBirth":"1984-10-06","rightArmedBowl":false,"rightHandedBat":false}],"wicketKeeper":{"id":127,"fullName":"Robin Uthappa","shortName":"R Uthappa","nationality":"Indian","dateOfBirth":"1985-11-11","rightArmedBowl":true,"rightHandedBat":true},"captain":{"id":84,"fullName":"Gautam Gambhir","shortName":"G Gambhir","nationality":"Indian","dateOfBirth":"1981-10-14","rightArmedBowl":false,"rightHandedBat":false}},{"id":4786,"team":{"id":4,"fullName":"Kings XI Punjab","shortName":"Kings XI","abbreviation":"KXIP","type":"m","primaryColor":"DA1F3D","secondaryColor":"FFFFFF"},"players":[{"id":7,"fullName":"Murali Vijay","shortName":"M Vijay","nationality":"Indian","dateOfBirth":"1984-04-01","rightArmedBowl":false,"rightHandedBat":false},{"id":1085,"fullName":"Manan Vohra","shortName":"M Vohra","nationality":"Indian","dateOfBirth":"1993-07-18","rightArmedBowl":false,"rightHandedBat":true},{"id":964,"fullName":"Marcus Stoinis","shortName":"MP Stoinis","nationality":"Australian","dateOfBirth":"1989-08-16","rightArmedBowl":false,"rightHandedBat":true},{"id":282,"fullName":"Glenn Maxwell","shortName":"G Maxwell","nationality":"Australian","dateOfBirth":"1988-10-14","rightArmedBowl":true,"rightHandedBat":true,"bowlingStyle":"OFF_SPIN"},{"id":187,"fullName":"David Miller","shortName":"D Miller","nationality":"South African","dateOfBirth":"1989-06-10","rightArmedBowl":false,"rightHandedBat":false},{"id":1113,"fullName":"Axar Patel","shortName":"A Patel","nationality":"Indian","dateOfBirth":"1994-01-20","rightArmedBowl":false,"rightHandedBat":false},{"id":16,"fullName":"Wriddhiman Saha","shortName":"W Saha","nationality":"Indian","dateOfBirth":"1984-10-24","rightArmedBowl":true,"rightHandedBat":true},{"id":253,"fullName":"Gurkeerat Mann Singh","shortName":"GM Singh","nationality":"Indian","dateOfBirth":"1990-06-29","rightArmedBowl":true,"rightHandedBat":true,"bowlingStyle":"OFF_SPIN"},{"id":1107,"fullName":"Mohit Sharma","shortName":"M Sharma","nationality":"Indian","dateOfBirth":"1991-12-19","rightArmedBowl":false,"rightHandedBat":true},{"id":1112,"fullName":"Sandeep Sharma","shortName":"Sandeep Sharma","nationality":"Indian","dateOfBirth":"1993-05-18","rightArmedBowl":false,"rightHandedBat":true},{"id":3180,"fullName":"Swapnil Singh","shortName":"S Singh","nationality":"Indian","dateOfBirth":"1991-01-22","rightArmedBowl":false,"rightHandedBat":true}],"wicketKeeper":{"id":16,"fullName":"Wriddhiman Saha","shortName":"W Saha","nationality":"Indian","dateOfBirth":"1984-10-24","rightArmedBowl":true,"rightHandedBat":true},"captain":{"id":7,"fullName":"Murali Vijay","shortName":"M Vijay","nationality":"Indian","dateOfBirth":"1984-04-01","rightArmedBowl":false,"rightHandedBat":false}}],"match":{"name":"ipl2016-32","tournamentId":{"id":3957,"name":"ipl2016","provisional":false},"id":4073},"description":"Match 32","battingOrder":[0,1],"isLimitedOvers":true,"lastUpdated":[1523967340528],"overs":20}