{"timestamp":"2015-04-15T20:00:00+0530","label":"Match 10","tournamentId":{"id":2785,"name":"ipl2015","provisional":false},"tournamentLabel":"IPL 2015","scheduleEntry":{"matchId":{"name":"ipl2015-10","tournamentId":{"id":2785,"name":"ipl2015","provisional":false},"id":3235},"description":"Match 10","matchDate":"2015-04-15T20:00:00+0530","matchType":"IPLT20","matchState":"C","highlightsLink":"http://www.iplt20.com/videos/media/id/4175257924001/m10-kxip-vs-dd-match-highlights","reportLink":"http://www.iplt20.com/news/2015/more-news/5986/report-m10-kxip-vs-dd","photostreamLink":"http://www.iplt20.com/photos/258/ipl-2015-match-10-kxip-v-dd","venue":{"id":7,"fullName":"Maharashtra Cricket Association\u0027s International Stadium","shortName":"Maharashtra Cricket Association\u0027s International Stadium","city":"Pune","country":"India"},"matchStatus":{"outcome":"B","text":"Delhi Daredevils won by 5 wickets"},"team1":{"team":{"id":4,"fullName":"Kings XI Punjab","shortName":"Kings XI","abbreviation":"KXIP","type":"m","primaryColor":"DA1F3D","secondaryColor":"FFFFFF"},"innings":[{"inningsNumber":1,"runs":165,"wkts":7,"ballsFaced":120,"maxBalls":120,"allOut":false,"declared":false}]},"team2":{"team":{"id":3,"fullName":"Delhi Daredevils","shortName":"Daredevils","abbreviation":"DD","type":"m","primaryColor":"004C93","secondaryColor":"F83430"},"innings":[{"inningsNumber":2,"runs":169,"wkts":5,"ballsFaced":119,"maxBalls":120,"allOut":false,"declared":false}]},"groupName":""},"resultOnly":false,"timestampMs":1429108200000,"endTimestampMs":1429119000000,"endTimestamp":"2015-04-15T23:00:00+0530"}