{"timestamp":"2012-04-11T20:00:00+0530","label":"Match 12","tournamentId":{"id":1,"name":"ipl2012","provisional":false},"tournamentLabel":"IPL 2012","scheduleEntry":{"matchId":{"name":"ipl2012-12","tournamentId":{"id":1,"name":"ipl2012","provisional":false},"id":13},"description":"Match 12","matchDate":"2012-04-11T20:00:00+0530","matchType":"IPLT20","matchState":"C","highlightsLink":"http://iplt20.com/videos?mid\u003db930c20d38514dd385bf0be48b32ab0b","reportLink":"http://iplt20.com/news/2012/match-reports/966/report-match-12-mi-v-rr","photostreamLink":"http://iplt20.com/photos/35/ipl-2012-match-12-mumbai-indians-v-rajasthan-royals","venue":{"id":4,"fullName":"Wankhede Stadium","shortName":"Wankhede Stadium","city":"Mumbai","country":"India"},"matchStatus":{"outcome":"A","text":"Mumbai Indians won by 27 runs"},"team1":{"team":{"id":6,"fullName":"Mumbai Indians","shortName":"Mumbai","abbreviation":"MI","type":"m","primaryColor":"00AEEF","secondaryColor":"FFFFFF"},"innings":[{"inningsNumber":1,"runs":197,"wkts":6,"ballsFaced":120,"maxBalls":120,"allOut":false,"declared":false}]},"team2":{"team":{"id":8,"fullName":"Rajasthan Royals","shortName":"Royals","abbreviation":"RR","type":"m","primaryColor":"004B8C","secondaryColor":"FFFFFF"},"innings":[{"inningsNumber":2,"runs":170,"wkts":10,"ballsFaced":118,"maxBalls":120,"allOut":true,"declared":false}]},"groupName":""},"resultOnly":false,"timestampMs":1334154600000,"endTimestampMs":1334165400000,"endTimestamp":"2012-04-11T23:00:00+0530"}